bdajax/__init__.py
bdajax/bdajax.pt
bdajax/bdajax_bs3.pt
bdajax/configure.zcml
bdajax/resources/bdajax.css
bdajax/resources/bdajax.js
bdajax/resources/bdajax_bs3.css
bdajax/resources/bdajax_bs3.js
bdajax/resources/close.png
bdajax/resources/error.png
bdajax/resources/info.png
bdajax/resources/loading-spokes.svg
bdajax/resources/overlay.js
bdajax/resources/warning.png
bdajax-1.14.dist-info/LICENSE.rst
bdajax-1.14.dist-info/METADATA
bdajax-1.14.dist-info/WHEEL
bdajax-1.14.dist-info/namespace_packages.txt
bdajax-1.14.dist-info/top_level.txt
bdajax-1.14.dist-info/RECORD
