Metadata-Version: 2.1
Name: bdajax
Version: 1.14
Summary: Ajax convenience.
Home-page: http://github.com/conestack/bdajax
Author: Cone Contributors
Author-email: dev@conestack.org
License: Simplified BSD
Platform: UNKNOWN
Classifier: Environment :: Web Environment
Classifier: Operating System :: OS Independent
Classifier: Programming Language :: JavaScript
Classifier: Topic :: Internet :: WWW/HTTP :: Dynamic Content
Requires-Dist: setuptools
